gc_data_storage
