Metadata-Version: 2.1
Name: gc-data-storage
Version: 2.1.0
Summary: Python utility for data storage in Google Cloud Environments.
Home-page: https://github.com/AymoneKouame/gc_data_storage/
Author: Aymone Jeanne Kouame
Author-email: aymone.jk@gmail.com
License: UNKNOWN
Platform: UNKNOWN
Classifier: Programming Language :: Python :: 3
Classifier: License :: OSI Approved :: MIT License
Classifier: Operating System :: OS Independent
Requires-Python: >=3.6
